.gitignore
setup.py
docs/Makefile
docs/conf.py
docs/index.rst
docs/make.bat
docs/tutorial.rst
docs/tutorial/sal_IC_fromWEBSERVICES
docs/tutorial/travis_county.dbf
docs/tutorial/travis_county.prj
docs/tutorial/travis_county.qpj
docs/tutorial/travis_county.shp
docs/tutorial/travis_county.shx
docs/tutorial/tut_example1.py
docs/tutorial/tutorial_intro.pptx
export/tceq_to_cache.py
export/tceq_to_database.py
extra/direct_cache_example.py
pyhis/__init__.py
pyhis/cache.py
pyhis/core.py
pyhis/exceptions.py
pyhis/his_central.py
pyhis/quantities.py
pyhis/shapefile.py
pyhis/util.py
pyhis/waterml.py
pyhis.egg-info/PKG-INFO
pyhis.egg-info/SOURCES.txt
pyhis.egg-info/dependency_links.txt
pyhis.egg-info/requires.txt
pyhis.egg-info/top_level.txt
test/test.py
test/twdb_wsdl.xml
test/usgs_wsdl.xml
test/shapefiles/pyhis_test.dbf
test/shapefiles/pyhis_test.prj
test/shapefiles/pyhis_test.qpj
test/shapefiles/pyhis_test.shp
test/shapefiles/pyhis_test.shx