Metadata-Version: 1.0
Name: pyhis
Version: 0.1.1-alpha
Summary: a python library for querying data via CUAHSI-HIS web services
Home-page: UNKNOWN
Author: Andy Wilson
Author-email: wilson.andrew.j@gmail.com
License: BSD
Keywords: his pyhis water waterml cuahsi wateroneflow
Platform: any
Classifier: Development Status :: 4 - Beta
Classifier: Intended Audience :: Science/Research
Classifier: License :: OSI Approved :: BSD License
Classifier: Operating System :: OS Independent
Classifier: Programming Language :: Python
Classifier: Topic :: Software Development :: Libraries :: Python Modules
